.gitignore
CHANGES.txt
MANIFEST.in
README.rst
bootstrap.py
buildout.cfg
collective.localrolesdatatables-configure.zcml
jenkins.cfg
setup.py
collective/__init__.py
collective.localrolesdatatables.egg-info/PKG-INFO
collective.localrolesdatatables.egg-info/SOURCES.txt
collective.localrolesdatatables.egg-info/dependency_links.txt
collective.localrolesdatatables.egg-info/entry_points.txt
collective.localrolesdatatables.egg-info/namespace_packages.txt
collective.localrolesdatatables.egg-info/not-zip-safe
collective.localrolesdatatables.egg-info/requires.txt
collective.localrolesdatatables.egg-info/top_level.txt
collective/localrolesdatatables/__init__.py
collective/localrolesdatatables/configure.zcml
collective/localrolesdatatables/localroles_view.js
collective/localrolesdatatables/localroles_view.pt
collective/localrolesdatatables/localroles_view.py
collective/localrolesdatatables/rebuild_i18n.sh
collective/localrolesdatatables/setuphandlers.py
collective/localrolesdatatables/testing.py
collective/localrolesdatatables/upgrades.py
collective/localrolesdatatables/upgrades.zcml
collective/localrolesdatatables/locales/collective.localrolesdatatables.pot
collective/localrolesdatatables/locales/en/LC_MESSAGES/collective.localrolesdatatables.po
collective/localrolesdatatables/locales/fr/LC_MESSAGES/collective.localrolesdatatables.po
collective/localrolesdatatables/profiles/default/catalog.xml
collective/localrolesdatatables/profiles/default/collective.localrolesdatatables.marker.txt
collective/localrolesdatatables/profiles/default/controlpanel.xml
collective/localrolesdatatables/profiles/default/cssregistry.xml
collective/localrolesdatatables/profiles/default/jsregistry.xml
collective/localrolesdatatables/profiles/default/metadata.xml
collective/localrolesdatatables/tests/__init__.py
collective/localrolesdatatables/tests/base.py
collective/localrolesdatatables/tests/test_localroles_view.py
collective/localrolesdatatables/tests/test_setup.py