Metadata-Version: 1.0
Name: collective.localrolesdatatables
Version: 1.0.1
Summary: View / export localroles of all or parts of the site
Home-page: https://github.com/collective/collective.localrolesdatatables
Author: JeanMichel FRANCOIS
Author-email: toutpt@gmail.com
License: GPL
Keywords: plone localroles datatables
Platform: UNKNOWN
Classifier: Programming Language :: Python
Classifier: Framework :: Plone
Classifier: Framework :: Plone :: 4.0
Classifier: Framework :: Plone :: 4.1
Classifier: Framework :: Plone :: 4.2
